cs2inspect/__init__.py
cs2inspect/_creation.py
cs2inspect/_hex.py
cs2inspect/_link_util.py
cs2inspect/_proto.py
cs2inspect/_rarity.py
cs2inspect/econ.proto
cs2inspect/econ_pb2.py
cs2inspect-0.2.4.dist-info/LICENSE
cs2inspect-0.2.4.dist-info/METADATA
cs2inspect-0.2.4.dist-info/WHEEL
cs2inspect-0.2.4.dist-info/RECORD
