Metadata-Version: 2.3
Name: cs2inspect
Version: 0.2.4
Summary: CS2 inspect link utility
License: GPL-3.0-or-later
Author: Lukas Mahler
Author-email: m@hler.eu
Requires-Python: >=3.9,<4.0
Classifier: License :: OSI Approved :: GNU General Public License v3 (GPLv3)
Classifier: License :: OSI Approved :: GNU General Public License v3 or later (GPLv3+)
Classifier: Operating System :: OS Independent
Classifier: Programming Language :: Python :: 3
Classifier: Programming Language :: Python :: 3.9
Classifier: Programming Language :: Python :: 3.10
Classifier: Programming Language :: Python :: 3.11
Classifier: Programming Language :: Python :: 3.12
Classifier: Programming Language :: Python :: 3.13
Requires-Dist: protobuf (>=5.27.3,<6.0.0)
Project-URL: Repository, https://github.com/Helyux/cs2inspect
